specwizard/Alternative_SpecWizard_Input.py
specwizard/Phys.py
specwizard/SimulationInputKeys.py
specwizard/SpecWizard_AnalyseOpticaldepth.py
specwizard/SpecWizard_Atomfile.py
specwizard/SpecWizard_BuildInput.py
specwizard/SpecWizard_ComputeOpticaldepth.py
specwizard/SpecWizard_Elements.py
specwizard/SpecWizard_Input.py
specwizard/SpecWizard_IonTables.py
specwizard/SpecWizard_IonizationBalance.py
specwizard/SpecWizard_Lines.py
specwizard/SpecWizard_Longspectra.py
specwizard/SpecWizard_ProjectData.py
specwizard/SpecWizard_Run_Cloudy.py
specwizard/SpecWizard_SaveOpticaldepth.py
specwizard/SpecWizard_SplineInterpolation.py
specwizard/SpecWizard_read_obs_data.py
specwizard/__init__.py
specwizard/h1damping.py
specwizard/reading_simulations.py
specwizard/specwizard.py
specwizard-0.9.5.0.dist-info/licenses/LICENSE
specwizard-0.9.5.0.dist-info/METADATA
specwizard-0.9.5.0.dist-info/WHEEL
specwizard-0.9.5.0.dist-info/top_level.txt
specwizard-0.9.5.0.dist-info/RECORD
