Metadata-Version: 2.4
Name: specwizard
Version: 0.9.5.0
Summary: .
Author-email: Andres Aramburo-Garcia <aramburo@lorentz.leidenuniv.nl>, Tom Theuns <tom.theuns@durham.ac.uk>
Project-URL: Homepage, https://github.com/specwizard/specwizard
Project-URL: Bug Tracker, https://github.com/specwizard/specwizard/issues
Classifier: Programming Language :: Python :: 3
Classifier: License :: OSI Approved :: GNU General Public License v3 (GPLv3)
Classifier: Operating System :: OS Independent
Requires-Python: >=3.7
License-File: LICENSE
Requires-Dist: numpy
Requires-Dist: scipy
Requires-Dist: swiftsimio
Requires-Dist: mendeleev
Requires-Dist: roman
Requires-Dist: swiftsimio
Requires-Dist: pyread_eagle
Requires-Dist: matplotlib
Requires-Dist: hydrangea
Requires-Dist: bs4
Requires-Dist: pyyaml
Requires-Dist: h5py
Requires-Dist: requests
Requires-Dist: html5lib
Requires-Dist: astropy
Dynamic: license-file
